CardGameBase/Card.py
CardGameBase/Deck.py
CardGameBase/Exceptions.py
CardGameBase/Hand.py
CardGameBase/Utility.py
CardGameBase/__init__.py
CardGameBase-1.0.6.dist-info/LICENSE
CardGameBase-1.0.6.dist-info/METADATA
CardGameBase-1.0.6.dist-info/WHEEL
CardGameBase-1.0.6.dist-info/top_level.txt
CardGameBase-1.0.6.dist-info/RECORD
