Metadata-Version: 2.1
Name: CardGameBase
Version: 1.0.6
Summary: Card Game Base with basic deck and card class
Home-page: https://github.com/DerSchinken/CardGameBase/
Author: DerSchinken
Maintainer: DerSchinken
Classifier: Intended Audience :: Developers
Classifier: Programming Language :: Python :: 3.7
Classifier: Programming Language :: Python :: 3.8
Classifier: Programming Language :: Python :: 3.9
Classifier: Programming Language :: Python :: 3.10
Classifier: Programming Language :: Python :: 3.11
Requires-Python: >= 3.7
License-File: LICENSE
